LICENSE.txt
MANIFEST.in
README.rst
setup.cfg
setup.py
mdfminer/__init__.py
mdfminer/mdf.py
mdfminer/mdftools.py
mdfminer.egg-info/PKG-INFO
mdfminer.egg-info/SOURCES.txt
mdfminer.egg-info/dependency_links.txt
mdfminer.egg-info/entry_points.txt
mdfminer.egg-info/requires.txt
mdfminer.egg-info/top_level.txt