Metadata-Version: 1.1
Name: mdfminer
Version: 0.0.4
Summary: A data miner for Measure Data File Format (.mdf)
Home-page: https://github.com/menschel/mdfminer.git
Author: Patrick Menschel
Author-email: menschel.p@posteo.de
License: GPL
Keywords: mdf measurement data file
Platform: UNKNOWN
Classifier: Development Status :: 4 - Beta
Classifier: Intended Audience :: Science/Research
Classifier: Topic :: Scientific/Engineering
Classifier: License :: OSI Approved :: GNU General Public License v3 or later (GPLv3+)
Classifier: Programming Language :: Python :: 3
Classifier: Programming Language :: Python :: 3.4
Classifier: Programming Language :: Python :: 3.5
Classifier: Operating System :: OS Independent
